mwdictionary/__init__.py
mwdictionary/client.py
mwdictionary/model.py
mwdictionary-0.1.2.dist-info/WHEEL
mwdictionary-0.1.2.dist-info/METADATA
mwdictionary-0.1.2.dist-info/RECORD
