Metadata-Version: 2.1
Name: mwdictionary
Version: 0.1.2
Summary: API Wrapper for the Merriam-Webster API.
Home-page: https://github.com/PederHA/mwdictionary
License: MIT
Author: Peder Hovdan Andresen
Requires-Python: >=3.7,<4.0
Classifier: License :: OSI Approved :: MIT License
Classifier: Programming Language :: Python :: 3
Classifier: Programming Language :: Python :: 3.7
Classifier: Programming Language :: Python :: 3.8
Requires-Dist: httpx (>=0.12.1,<0.13.0)
Project-URL: Repository, https://github.com/PederHA/mwdictionary
